frankentile/__init__.py
frankentile/_discord.py
frankentile/auto_desk.py
frankentile/auto_desk_api.py
frankentile/discord_bot.py
frankentile/discord_log.py
frankentile/gen_keybinding_img.py
frankentile/grafana.py
frankentile/tmux.py
frankentile/web.py
frankentile-0.3.1.dist-info/LICENSE
frankentile-0.3.1.dist-info/METADATA
frankentile-0.3.1.dist-info/WHEEL
frankentile-0.3.1.dist-info/top_level.txt
frankentile-0.3.1.dist-info/RECORD
