Metadata-Version: 2.1
Name: frankentile
Version: 0.3.1
Summary: a qtile configuration lib that is unnecessarily over the top.
Author-email: Eoghan West <eowest@gmail.com>
License: MIT License
Project-URL: Homepage, https://github.com/calacuda/frankensteins-qtile
Project-URL: Bug Tracker, https://github.com/calacuda/frankensteins-qtile/issues
Classifier: Development Status :: 4 - Beta
Classifier: Intended Audience :: End Users/Desktop
Classifier: License :: OSI Approved :: MIT License
Classifier: Operating System :: POSIX :: Linux
Classifier: Programming Language :: Python :: 3.11
Classifier: Programming Language :: Python :: 3.10
Classifier: Programming Language :: Python :: 3.9
License-File: LICENSE
Requires-Dist: flask[async]
Requires-Dist: discord
Requires-Dist: auto-tmux
Requires-Dist: pycairo
Requires-Dist: PyGObject
Requires-Dist: pyalsaaudio
Requires-Dist: libtmux
